polititweet/__init__.py
polititweet/polititweet.py
polititweet-0.0.1.dist-info/METADATA
polititweet-0.0.1.dist-info/WHEEL
polititweet-0.0.1.dist-info/licenses/LICENSE
polititweet-0.0.1.dist-info/RECORD
