Metadata-Version: 2.1
Name: polititweet
Version: 0.0.1
Summary: A twint addon to simplify political tweet scraping
Project-URL: Homepage, https://github.com/mlawsonking/PoliticianTweeting
Project-URL: Bug Tracker, https://github.com/mlawsonking/PoliticianTweeting
Author-email: Michael King <mlawsonking@gmail.com>
License: Copyright (c) 2018 The Python Packaging Authority
Classifier: License :: OSI Approved :: MIT License
Classifier: Operating System :: OS Independent
Classifier: Programming Language :: Python :: 3
Requires-Python: >=3.7
